PyQt6/Qt6/qsci/api/python/PyQt6-WebEngine.api
PyQt6/QtWebEngineCore.abi3.so
PyQt6/QtWebEngineCore.pyi
PyQt6/QtWebEngineQuick.abi3.so
PyQt6/QtWebEngineQuick.pyi
PyQt6/QtWebEngineWidgets.abi3.so
PyQt6/QtWebEngineWidgets.pyi
PyQt6/bindings/QtWebEngineCore/QtWebEngineCore.toml
PyQt6/bindings/QtWebEngineCore/QtWebEngineCoremod.sip
PyQt6/bindings/QtWebEngineCore/qtwebenginecoreglobal.sip
PyQt6/bindings/QtWebEngineCore/qwebenginecertificateerror.sip
PyQt6/bindings/QtWebEngineCore/qwebengineclientcertificateselection.sip
PyQt6/bindings/QtWebEngineCore/qwebengineclientcertificatestore.sip
PyQt6/bindings/QtWebEngineCore/qwebengineclienthints.sip
PyQt6/bindings/QtWebEngineCore/qwebenginecontextmenurequest.sip
PyQt6/bindings/QtWebEngineCore/qwebenginecookiestore.sip
PyQt6/bindings/QtWebEngineCore/qwebenginedesktopmediarequest.sip
PyQt6/bindings/QtWebEngineCore/qwebenginedownloadrequest.sip
PyQt6/bindings/QtWebEngineCore/qwebengineextensioninfo.sip
PyQt6/bindings/QtWebEngineCore/qwebengineextensionmanager.sip
PyQt6/bindings/QtWebEngineCore/qwebenginefilesystemaccessrequest.sip
PyQt6/bindings/QtWebEngineCore/qwebenginefindtextresult.sip
PyQt6/bindings/QtWebEngineCore/qwebengineframe.sip
PyQt6/bindings/QtWebEngineCore/qwebenginefullscreenrequest.sip
PyQt6/bindings/QtWebEngineCore/qwebengineglobalsettings.sip
PyQt6/bindings/QtWebEngineCore/qwebenginehistory.sip
PyQt6/bindings/QtWebEngineCore/qwebenginehttprequest.sip
PyQt6/bindings/QtWebEngineCore/qwebengineloadinginfo.sip
PyQt6/bindings/QtWebEngineCore/qwebenginenavigationrequest.sip
PyQt6/bindings/QtWebEngineCore/qwebenginenewwindowrequest.sip
PyQt6/bindings/QtWebEngineCore/qwebenginenotification.sip
PyQt6/bindings/QtWebEngineCore/qwebenginepage.sip
PyQt6/bindings/QtWebEngineCore/qwebenginepermission.sip
PyQt6/bindings/QtWebEngineCore/qwebengineprofile.sip
PyQt6/bindings/QtWebEngineCore/qwebengineprofilebuilder.sip
PyQt6/bindings/QtWebEngineCore/qwebenginequotarequest.sip
pyqt6_webengine-6.10.0.dist-info/licenses/LICENSE
pyqt6_webengine-6.10.0.dist-info/WHEEL
pyqt6_webengine-6.10.0.dist-info/METADATA
pyqt6_webengine-6.10.0.dist-info/RECORD
